{"gridSize":{"x":6,"y":6},"levelDifficulty":2,"pieces":[{"vertices":[{"x":-2.5,"y":3.0,"z":0.0},{"x":-3.0,"y":3.0,"z":0.0},{"x":-3.0,"y":3.5,"z":0.0},{"x":-3.0,"y":2.5,"z":0.0},{"x":-2.5,"y":2.5,"z":0.0},{"x":-2.0,"y":2.5,"z":0.0},{"x":-2.0,"y":3.0,"z":0.0},{"x":-2.0,"y":3.5,"z":0.0},{"x":-2.5,"y":3.5,"z":0.0},{"x":-1.5,"y":3.0,"z":0.0},{"x":-1.5,"y":3.5,"z":0.0},{"x":-1.0,"y":3.5,"z":0.0},{"x":-1.0,"y":3.0,"z":0.0},{"x":-1.0,"y":2.5,"z":0.0},{"x":-1.5,"y":2.5,"z":0.0},{"x":-0.5,"y":3.0,"z":0.0}],"triangles":[0,1,2,0,3,1,0,4,3,0,5,4,0,6,5,0,7,6,0,8,7,0,2,8,9,6,7,9,7,10,9,10,11,9,11,12,9,12,13,9,13,14,9,14,5,9,5,6,15,13,12,15,12,11],"origin":{"x":-1.90625,"y":3.0,"z":0.0},"color":{"r":0.23529411852359773,"g":0.3843137323856354,"b":0.3333333432674408,"a":1.0}},{"vertices":[{"x":-0.5,"y":3.0,"z":0.0},{"x":-1.0,"y":3.5,"z":0.0},{"x":-0.5,"y":3.5,"z":0.0},{"x":0.0,"y":3.5,"z":0.0},{"x":0.0,"y":3.0,"z":0.0},{"x":0.5,"y":3.0,"z":0.0},{"x":0.5,"y":3.5,"z":0.0},{"x":1.0,"y":3.5,"z":0.0},{"x":1.0,"y":3.0,"z":0.0},{"x":1.0,"y":2.5,"z":0.0},{"x":0.5,"y":2.5,"z":0.0},{"x":0.5,"y":2.0,"z":0.0},{"x":1.0,"y":1.5,"z":0.0},{"x":0.5,"y":1.5,"z":0.0},{"x":0.0,"y":1.5,"z":0.0},{"x":0.0,"y":2.0,"z":0.0},{"x":0.0,"y":2.5,"z":0.0},{"x":-0.5,"y":2.5,"z":0.0},{"x":-1.0,"y":2.5,"z":0.0}],"triangles":[0,1,2,0,2,3,0,3,4,5,4,3,5,3,6,5,6,7,5,7,8,5,8,9,5,9,10,11,10,9,11,12,13,11,13,14,11,14,15,11,15,16,11,16,10,5,10,16,5,16,4,0,4,16,0,16,17,0,17,18],"origin":{"x":0.15789473056793214,"y":2.6578948497772219,"z":0.0},"color":{"r":0.5098039507865906,"g":0.6666666865348816,"b":0.8901960849761963,"a":1.0}},{"vertices":[{"x":-0.5,"y":2.0,"z":0.0},{"x":0.0,"y":2.5,"z":0.0},{"x":0.0,"y":2.0,"z":0.0},{"x":-0.5,"y":2.5,"z":0.0},{"x":-1.0,"y":2.5,"z":0.0},{"x":-1.0,"y":2.0,"z":0.0},{"x":-1.5,"y":2.0,"z":0.0},{"x":-1.5,"y":2.5,"z":0.0},{"x":-2.0,"y":2.5,"z":0.0},{"x":-2.0,"y":2.0,"z":0.0},{"x":-2.5,"y":2.0,"z":0.0},{"x":-2.5,"y":2.5,"z":0.0},{"x":-3.0,"y":2.5,"z":0.0},{"x":-3.0,"y":2.0,"z":0.0},{"x":-3.0,"y":1.5,"z":0.0},{"x":-2.5,"y":1.5,"z":0.0},{"x":-2.0,"y":1.5,"z":0.0},{"x":-1.5,"y":1.5,"z":0.0},{"x":-1.0,"y":1.5,"z":0.0},{"x":-0.5,"y":1.5,"z":0.0},{"x":0.0,"y":1.5,"z":0.0},{"x":-1.5,"y":1.0,"z":0.0},{"x":-2.0,"y":1.0,"z":0.0},{"x":-2.0,"y":0.5,"z":0.0},{"x":-1.5,"y":0.5,"z":0.0},{"x":-1.0,"y":0.5,"z":0.0},{"x":-1.0,"y":1.0,"z":0.0}],"triangles":[0,1,2,0,3,1,0,4,3,0,5,4,6,4,5,6,7,4,6,8,7,6,9,8,10,8,9,10,11,8,10,12,11,10,13,12,10,14,13,10,15,14,10,16,15,10,9,16,6,16,9,6,17,16,6,18,17,6,5,18,0,18,5,0,19,18,0,20,19,0,2,20,21,16,17,21,22,16,21,23,22,21,24,23,21,25,24,21,26,25,21,18,26,21,17,18],"origin":{"x":-1.5,"y":1.7222222089767457,"z":0.0},"color":{"r":0.9372549057006836,"g":0.6392157077789307,"b":0.7843137383460999,"a":1.0}},{"vertices":[{"x":-2.5,"y":1.0,"z":0.0},{"x":-2.0,"y":1.5,"z":0.0},{"x":-2.0,"y":1.0,"z":0.0},{"x":-2.0,"y":0.5,"z":0.0},{"x":-2.5,"y":1.5,"z":0.0},{"x":-3.0,"y":1.5,"z":0.0},{"x":-3.0,"y":1.0,"z":0.0},{"x":-3.0,"y":0.5,"z":0.0},{"x":-2.5,"y":0.5,"z":0.0},{"x":-2.5,"y":0.0,"z":0.0},{"x":-2.0,"y":0.0,"z":0.0},{"x":-2.0,"y":-0.5,"z":0.0},{"x":-2.5,"y":-0.5,"z":0.0},{"x":-3.0,"y":-0.5,"z":0.0},{"x":-3.0,"y":0.0,"z":0.0},{"x":-2.5,"y":-1.0,"z":0.0},{"x":-2.0,"y":-1.0,"z":0.0},{"x":-2.0,"y":-1.5,"z":0.0},{"x":-2.5,"y":-1.5,"z":0.0},{"x":-3.0,"y":-1.5,"z":0.0},{"x":-3.0,"y":-1.0,"z":0.0},{"x":-1.5,"y":-1.0,"z":0.0}],"triangles":[0,1,2,0,2,3,0,4,1,0,5,4,0,6,5,0,7,6,0,8,7,9,7,8,9,8,3,0,3,8,9,3,10,9,10,11,9,11,12,9,12,13,9,13,14,9,14,7,15,12,11,15,11,16,15,16,17,15,17,18,15,18,19,15,19,20,15,20,13,15,13,12,21,17,16,21,16,11],"origin":{"x":-2.454545497894287,"y":-0.04545454680919647,"z":0.0},"color":{"r":1.0,"g":0.545098066329956,"b":0.07450980693101883,"a":1.0}},{"vertices":[{"x":-1.5,"y":0.0,"z":0.0},{"x":-2.0,"y":0.5,"z":0.0},{"x":-1.5,"y":0.5,"z":0.0},{"x":-2.0,"y":0.0,"z":0.0},{"x":-2.0,"y":-0.5,"z":0.0},{"x":-1.5,"y":-0.5,"z":0.0},{"x":-1.0,"y":-0.5,"z":0.0},{"x":-1.0,"y":0.0,"z":0.0},{"x":-1.0,"y":0.5,"z":0.0},{"x":-1.5,"y":-1.0,"z":0.0},{"x":-1.0,"y":-1.0,"z":0.0},{"x":-1.0,"y":-1.5,"z":0.0},{"x":-1.5,"y":-1.5,"z":0.0},{"x":-2.0,"y":-1.5,"z":0.0},{"x":-1.5,"y":-2.0,"z":0.0},{"x":-1.0,"y":-2.0,"z":0.0},{"x":-1.0,"y":-2.5,"z":0.0},{"x":-1.5,"y":-2.5,"z":0.0},{"x":-2.0,"y":-2.5,"z":0.0},{"x":-2.0,"y":-2.0,"z":0.0},{"x":-2.5,"y":-2.0,"z":0.0},{"x":-2.5,"y":-1.5,"z":0.0},{"x":-3.0,"y":-1.5,"z":0.0},{"x":-3.0,"y":-2.0,"z":0.0},{"x":-3.0,"y":-2.5,"z":0.0},{"x":-2.5,"y":-2.5,"z":0.0},{"x":-0.5,"y":0.0,"z":0.0},{"x":-0.5,"y":-2.0,"z":0.0}],"triangles":[0,1,2,0,3,1,0,4,3,0,5,4,0,6,5,0,7,6,0,8,7,0,2,8,9,5,6,9,4,5,9,6,10,9,10,11,9,11,12,9,12,13,14,12,11,14,11,15,14,15,16,14,16,17,14,17,18,14,18,19,14,19,13,14,13,12,20,13,19,20,21,13,20,22,21,20,23,22,20,24,23,20,25,24,20,18,25,20,19,18,26,6,7,26,7,8,27,16,15,27,15,11],"origin":{"x":-1.6785714626312256,"y":-1.2142857313156129,"z":0.0},"color":{"r":0.5,"g":0.5,"b":0.5,"a":1.0}},{"vertices":[{"x":-0.5,"y":0.0,"z":0.0},{"x":-1.0,"y":0.5,"z":0.0},{"x":-0.5,"y":0.5,"z":0.0},{"x":0.0,"y":0.5,"z":0.0},{"x":0.0,"y":0.0,"z":0.0},{"x":0.0,"y":-0.5,"z":0.0},{"x":-0.5,"y":-0.5,"z":0.0},{"x":-1.0,"y":-0.5,"z":0.0},{"x":-0.5,"y":-1.0,"z":0.0},{"x":-1.0,"y":-1.0,"z":0.0},{"x":-1.0,"y":-1.5,"z":0.0},{"x":-0.5,"y":-1.5,"z":0.0},{"x":0.0,"y":-1.5,"z":0.0},{"x":0.0,"y":-1.0,"z":0.0},{"x":-0.5,"y":-2.0,"z":0.0},{"x":0.0,"y":-2.0,"z":0.0},{"x":0.0,"y":-2.5,"z":0.0},{"x":-0.5,"y":-2.5,"z":0.0},{"x":-1.0,"y":-2.5,"z":0.0},{"x":-0.5,"y":1.0,"z":0.0},{"x":-1.0,"y":1.0,"z":0.0},{"x":-1.0,"y":1.5,"z":0.0},{"x":-0.5,"y":1.5,"z":0.0},{"x":0.0,"y":1.5,"z":0.0},{"x":0.0,"y":1.0,"z":0.0},{"x":0.5,"y":1.0,"z":0.0},{"x":0.5,"y":1.5,"z":0.0},{"x":1.0,"y":1.5,"z":0.0},{"x":1.0,"y":1.0,"z":0.0},{"x":1.0,"y":0.5,"z":0.0},{"x":0.5,"y":0.5,"z":0.0},{"x":1.5,"y":1.0,"z":0.0},{"x":1.5,"y":1.5,"z":0.0},{"x":2.0,"y":1.5,"z":0.0},{"x":2.0,"y":1.0,"z":0.0},{"x":2.0,"y":0.5,"z":0.0},{"x":1.5,"y":0.5,"z":0.0}],"triangles":[0,1,2,0,2,3,0,3,4,0,4,5,0,5,6,0,6,7,8,7,6,8,9,7,8,10,9,8,11,10,8,12,11,8,5,13,8,6,5,14,11,12,14,12,15,14,15,16,14,16,17,14,17,18,14,10,11,19,2,1,19,1,20,19,20,21,19,21,22,19,22,23,19,23,24,19,24,3,19,3,2,25,24,23,25,23,26,25,26,27,25,27,28,25,28,29,25,29,30,25,30,3,25,3,24,31,28,27,31,27,32,31,32,33,31,33,34,31,34,35,31,35,36,31,36,29,31,29,28,8,13,12],"origin":{"x":0.09459459781646729,"y":0.013513513840734959,"z":0.0},"color":{"r":1.0,"g":1.0,"b":1.0,"a":1.0}},{"vertices":[{"x":0.5,"y":0.0,"z":0.0},{"x":0.0,"y":0.0,"z":0.0},{"x":0.0,"y":0.5,"z":0.0},{"x":0.5,"y":0.5,"z":0.0},{"x":1.0,"y":0.5,"z":0.0},{"x":1.0,"y":0.0,"z":0.0},{"x":1.5,"y":0.0,"z":0.0},{"x":1.5,"y":0.5,"z":0.0},{"x":2.0,"y":0.5,"z":0.0},{"x":2.0,"y":0.0,"z":0.0},{"x":2.5,"y":0.0,"z":0.0},{"x":2.5,"y":0.5,"z":0.0},{"x":3.0,"y":0.5,"z":0.0},{"x":3.0,"y":0.0,"z":0.0},{"x":3.0,"y":-0.5,"z":0.0},{"x":2.5,"y":-0.5,"z":0.0},{"x":2.0,"y":-0.5,"z":0.0},{"x":1.5,"y":-0.5,"z":0.0},{"x":1.0,"y":-0.5,"z":0.0},{"x":0.5,"y":-0.5,"z":0.0},{"x":0.0,"y":-0.5,"z":0.0},{"x":2.5,"y":-1.0,"z":0.0},{"x":2.0,"y":-1.0,"z":0.0},{"x":2.0,"y":-1.5,"z":0.0},{"x":2.5,"y":-1.5,"z":0.0},{"x":2.5,"y":-2.0,"z":0.0},{"x":2.0,"y":-2.0,"z":0.0},{"x":2.0,"y":-2.5,"z":0.0},{"x":2.5,"y":-2.5,"z":0.0},{"x":3.0,"y":-2.5,"z":0.0},{"x":3.0,"y":-2.0,"z":0.0},{"x":3.0,"y":-1.5,"z":0.0},{"x":3.0,"y":-1.0,"z":0.0}],"triangles":[0,1,2,0,2,3,0,3,4,0,4,5,6,5,4,6,4,7,6,7,8,6,8,9,10,9,8,10,8,11,10,11,12,10,12,13,10,13,14,10,14,15,10,15,16,10,16,9,6,9,16,6,16,17,6,17,18,6,18,5,0,5,18,0,18,19,0,19,20,0,20,1,21,16,15,21,22,16,21,23,22,21,24,23,25,23,24,25,26,23,25,27,26,25,28,27,25,29,28,25,30,29,25,31,30,25,24,31,21,31,24,21,32,31,21,14,32,21,15,14],"origin":{"x":1.8636363744735718,"y":-0.6363636255264282,"z":0.0},"color":{"r":1.0,"g":0.0,"b":1.0,"a":1.0}},{"vertices":[{"x":0.5,"y":-1.0,"z":0.0},{"x":0.0,"y":-1.0,"z":0.0},{"x":0.0,"y":-0.5,"z":0.0},{"x":0.5,"y":-0.5,"z":0.0},{"x":1.0,"y":-0.5,"z":0.0},{"x":1.0,"y":-1.5,"z":0.0},{"x":0.5,"y":-1.5,"z":0.0},{"x":0.0,"y":-1.5,"z":0.0},{"x":0.5,"y":-2.0,"z":0.0},{"x":0.0,"y":-2.0,"z":0.0},{"x":0.0,"y":-2.5,"z":0.0},{"x":0.5,"y":-2.5,"z":0.0},{"x":1.0,"y":-2.5,"z":0.0},{"x":1.0,"y":-2.0,"z":0.0},{"x":1.5,"y":-2.0,"z":0.0}],"triangles":[0,1,2,0,2,3,0,3,4,0,5,6,0,6,7,0,7,1,8,7,6,8,9,7,8,10,9,8,11,10,8,12,11,8,13,12,8,5,13,8,6,5,14,12,13,14,13,5],"origin":{"x":0.5333333611488342,"y":-1.5666667222976685,"z":0.0},"color":{"r":1.0,"g":0.9215686321258545,"b":0.01568627543747425,"a":1.0}},{"vertices":[{"x":0.5,"y":-1.0,"z":0.0},{"x":1.0,"y":-1.0,"z":0.0},{"x":1.0,"y":-1.5,"z":0.0},{"x":1.0,"y":-0.5,"z":0.0},{"x":1.5,"y":-1.0,"z":0.0},{"x":1.5,"y":-0.5,"z":0.0},{"x":2.0,"y":-0.5,"z":0.0},{"x":2.0,"y":-1.0,"z":0.0},{"x":2.0,"y":-1.5,"z":0.0},{"x":1.5,"y":-1.5,"z":0.0},{"x":1.5,"y":-2.0,"z":0.0},{"x":2.0,"y":-2.0,"z":0.0},{"x":2.0,"y":-2.5,"z":0.0},{"x":1.5,"y":-2.5,"z":0.0},{"x":1.0,"y":-2.5,"z":0.0}],"triangles":[0,1,2,0,3,1,4,1,3,4,3,5,4,5,6,4,6,7,4,7,8,4,8,9,4,9,2,4,2,1,10,2,9,10,9,8,10,8,11,10,11,12,10,12,13,10,13,14],"origin":{"x":1.4666666984558106,"y":-1.4333332777023316,"z":0.0},"color":{"r":0.0,"g":1.0,"b":0.0,"a":1.0}},{"vertices":[{"x":2.5,"y":1.0,"z":0.0},{"x":2.0,"y":0.5,"z":0.0},{"x":2.0,"y":1.0,"z":0.0},{"x":2.5,"y":0.5,"z":0.0},{"x":3.0,"y":0.5,"z":0.0},{"x":3.0,"y":1.0,"z":0.0},{"x":3.0,"y":1.5,"z":0.0},{"x":2.5,"y":1.5,"z":0.0},{"x":2.0,"y":1.5,"z":0.0},{"x":2.5,"y":2.0,"z":0.0},{"x":3.0,"y":2.0,"z":0.0},{"x":3.0,"y":2.5,"z":0.0},{"x":2.0,"y":2.0,"z":0.0},{"x":2.0,"y":2.5,"z":0.0}],"triangles":[0,1,2,0,3,1,0,4,3,0,5,4,0,6,5,0,7,6,0,8,7,0,2,8,9,6,7,9,10,6,9,11,10,9,12,13,9,8,12,9,7,8],"origin":{"x":2.5,"y":1.4285714626312256,"z":0.0},"color":{"r":0.0,"g":1.0,"b":1.0,"a":1.0}},{"vertices":[{"x":1.5,"y":2.0,"z":0.0},{"x":2.0,"y":2.5,"z":0.0},{"x":2.0,"y":2.0,"z":0.0},{"x":2.0,"y":1.5,"z":0.0},{"x":1.5,"y":1.5,"z":0.0},{"x":1.0,"y":1.5,"z":0.0},{"x":1.0,"y":2.0,"z":0.0},{"x":1.0,"y":2.5,"z":0.0},{"x":1.5,"y":2.5,"z":0.0},{"x":0.5,"y":2.0,"z":0.0}],"triangles":[0,1,2,0,2,3,0,3,4,0,4,5,0,5,6,0,6,7,0,7,8,0,8,1,9,7,6,9,6,5],"origin":{"x":1.399999976158142,"y":2.0,"z":0.0},"color":{"r":1.0,"g":0.0,"b":0.0,"a":1.0}},{"vertices":[{"x":1.5,"y":3.0,"z":0.0},{"x":1.5,"y":2.5,"z":0.0},{"x":1.0,"y":2.5,"z":0.0},{"x":1.0,"y":3.0,"z":0.0},{"x":1.0,"y":3.5,"z":0.0},{"x":1.5,"y":3.5,"z":0.0},{"x":2.0,"y":3.5,"z":0.0},{"x":2.0,"y":3.0,"z":0.0},{"x":2.5,"y":3.0,"z":0.0},{"x":2.5,"y":3.5,"z":0.0},{"x":3.0,"y":3.5,"z":0.0},{"x":3.0,"y":3.0,"z":0.0},{"x":3.0,"y":2.5,"z":0.0},{"x":2.5,"y":2.5,"z":0.0},{"x":2.0,"y":2.5,"z":0.0},{"x":2.5,"y":2.0,"z":0.0}],"triangles":[0,1,2,0,2,3,0,3,4,0,4,5,0,5,6,0,6,7,8,7,6,8,6,9,8,9,10,8,10,11,8,11,12,8,12,13,8,13,14,8,14,7,0,7,14,0,14,1,15,13,12,15,14,13],"origin":{"x":2.03125,"y":2.9375,"z":0.0},"color":{"r":0.0,"g":0.0,"b":1.0,"a":1.0}}],"origin":{"x":0.0,"y":3.0,"z":0.0}}